rawdatarinator/twixread_pyx.cpython-38-i386-linux-gnu.so
rawdatarinator/writecfl.cpython-38-i386-linux-gnu.so
rawdatarinator/readcfl.cpython-38-i386-linux-gnu.so
rawdatarinator/__init__.py
rawdatarinator/examples/simple.py
rawdatarinator/examples/__init__.py
rawdatarinator-1.4.0.dist-info/METADATA
rawdatarinator-1.4.0.dist-info/LICENSE.txt
rawdatarinator-1.4.0.dist-info/top_level.txt
rawdatarinator-1.4.0.dist-info/WHEEL
rawdatarinator-1.4.0.dist-info/RECORD
