Metadata-Version: 1.2
Name: rawdatarinator
Version: 1.4.0
Summary: Read Siemens raw data.
Home-page: https://github.com/mckib2/rawdatarinator
Author: Nicholas McKibben
Author-email: nicholas.bgp@gmail.com
License: GPL
Platform: UNKNOWN
Requires-Python: >=3.7
